{
  "version": "0.3.14-fixed",
  "steps": [
    {
      "tag": "CreateField",
      "model": "DasriForm",
      "field": "transporterWasteRefusedQuantity",
      "type": "Int",
      "arity": "Optional"
    },
    {
      "tag": "CreateField",
      "model": "DasriForm",
      "field": "recipientWasteRefusedQuantity",
      "type": "Int",
      "arity": "Optional"
    },
    {
      "tag": "CreateField",
      "model": "DasriForm",
      "field": "recipientWasteVolume",
      "type": "Int",
      "arity": "Optional"
    },
    {
      "tag": "DeleteField",
      "model": "DasriForm",
      "field": "recipientWasteRefusalQuantity"
    }
  ]
}